{
  "info": {
    "description": "data",
    "version": "1.0",
    "year": 2025,
    "contributor": "search engine",
    "source": "augmented",
    "license": {
      "name": "Creative Commons Attribution 4.0 International",
      "url": "https://creativecommons.org/licenses/by/4.0/"
    }
  },
  "images": [
    {
      "id": 4990379617,
      "width": 256,
      "height": 256,
      "file_name": "image (824).JPG",
      "size": 20931,
      "format": "JPG",
      "url": "",
      "hash": "",
      "status": "success"
    }
  ],
  "annotations": [
    {
      "id": 2198230624,
      "image_id": 4990379617,
      "category_id": 1000000033,
      "segmentation": [],
      "area": 119,
      "bbox": [
        117,
        206,
        26,
        18
      ]
    },
    {
      "id": 9236640624,
      "image_id": 4990379617,
      "category_id": 1000000033,
      "segmentation": [],
      "area": 198,
      "bbox": [
        167,
        208,
        16,
        16
      ]
    },
    {
      "id": 8660564624,
      "image_id": 4990379617,
      "category_id": 1000000033,
      "segmentation": [],
      "area": 125,
      "bbox": [
        134,
        199,
        17,
        11
      ]
    },
    {
      "id": 9656529624,
      "image_id": 4990379617,
      "category_id": 1000000033,
      "segmentation": [],
      "area": 1110,
      "bbox": [
        187,
        143,
        54,
        57
      ]
    },
    {
      "id": 1941992624,
      "image_id": 4990379617,
      "category_id": 1000000033,
      "segmentation": [],
      "area": 136,
      "bbox": [
        113,
        176,
        22,
        12
      ]
    },
    {
      "id": 6056669624,
      "image_id": 4990379617,
      "category_id": 1000000033,
      "segmentation": [],
      "area": 162,
      "bbox": [
        146,
        159,
        18,
        23
      ]
    },
    {
      "id": 3270588624,
      "image_id": 4990379617,
      "category_id": 1000000033,
      "segmentation": [],
      "area": 6590,
      "bbox": [
        31,
        1,
        210,
        141
      ]
    }
  ],
  "categories": [
    {
      "id": 1000000033,
      "name": "Septoria_leaf_spot",
      "supercategory": "Tomato"
    }
  ]
}