{
  "info": {
    "description": "data",
    "version": "1.0",
    "year": 2025,
    "contributor": "search engine",
    "source": "augmented",
    "license": {
      "name": "Creative Commons Attribution 4.0 International",
      "url": "https://creativecommons.org/licenses/by/4.0/"
    }
  },
  "images": [
    {
      "id": 7494414231,
      "width": 256,
      "height": 256,
      "file_name": "bb3b17dd-b745-4706-8e03-ff2660d77c23___Crnl_L.Mold 6512.JPG",
      "size": 18640,
      "format": "JPG",
      "url": "",
      "hash": "",
      "status": "success",
      "original_filename": "Crnl_L.Mold 6512.JPG",
      "pvc_filename": "bb3b17dd-b745-4706-8e03-ff2660d77c23___Crnl_L.Mold 6512.JPG"
    }
  ],
  "annotations": [
    {
      "id": 3033312237,
      "image_id": 7494414231,
      "category_id": 1000000032,
      "segmentation": [],
      "area": 1583,
      "bbox": [
        105,
        160,
        121,
        86
      ]
    },
    {
      "id": 9185937237,
      "image_id": 7494414231,
      "category_id": 1000000032,
      "segmentation": [],
      "area": 4180,
      "bbox": [
        60,
        46,
        78,
        122
      ]
    },
    {
      "id": 1448663237,
      "image_id": 7494414231,
      "category_id": 1000000032,
      "segmentation": [],
      "area": 152,
      "bbox": [
        176,
        139,
        13,
        16
      ]
    },
    {
      "id": 6520758237,
      "image_id": 7494414231,
      "category_id": 1000000032,
      "segmentation": [],
      "area": 134,
      "bbox": [
        107,
        121,
        12,
        18
      ]
    },
    {
      "id": 9455998237,
      "image_id": 7494414231,
      "category_id": 1000000032,
      "segmentation": [],
      "area": 228,
      "bbox": [
        188,
        102,
        29,
        24
      ]
    },
    {
      "id": 8090471237,
      "image_id": 7494414231,
      "category_id": 1000000032,
      "segmentation": [],
      "area": 555,
      "bbox": [
        0,
        69,
        50,
        18
      ]
    },
    {
      "id": 1103549237,
      "image_id": 7494414231,
      "category_id": 1000000032,
      "segmentation": [],
      "area": 532,
      "bbox": [
        106,
        21,
        66,
        21
      ]
    },
    {
      "id": 6266213237,
      "image_id": 7494414231,
      "category_id": 1000000032,
      "segmentation": [],
      "area": 322,
      "bbox": [
        48,
        12,
        33,
        18
      ]
    }
  ],
  "categories": [
    {
      "id": 1000000032,
      "name": "Leaf_Mold",
      "supercategory": "Tomato"
    }
  ]
}