{
  "info": {
    "description": "data",
    "version": "1.0",
    "year": 2025,
    "contributor": "search engine",
    "source": "no_augmentation",
    "license": {
      "name": "Creative Commons Attribution 4.0 International",
      "url": "https://creativecommons.org/licenses/by/4.0/"
    },
    "leaf_info": {
      "leaf_number": 258.0,
      "source": "plant_village_classification",
      "original_filename": "Com.G_SpM_FL 8799.JPG"
    }
  },
  "images": [
    {
      "id": 3590137603,
      "width": 256,
      "height": 256,
      "file_name": "image (1622).JPG",
      "size": 20425,
      "format": "JPG",
      "url": "",
      "hash": "",
      "status": "success",
      "original_filename": "Com.G_SpM_FL 8799.JPG",
      "pvc_filename": "f4788089-544c-42c7-ac09-9ede28bca5f4___Com.G_SpM_FL 8799.JPG"
    }
  ],
  "annotations": [
    {
      "id": 4114213611,
      "image_id": 3590137603,
      "category_id": 2000000034,
      "segmentation": [],
      "area": 30323,
      "bbox": [
        0,
        0,
        256,
        256
      ]
    },
    {
      "id": 9822107611,
      "image_id": 3590137603,
      "category_id": 2000000034,
      "segmentation": [],
      "area": 625,
      "bbox": [
        0,
        48,
        32,
        48
      ]
    },
    {
      "id": 6393296611,
      "image_id": 3590137603,
      "category_id": 2000000034,
      "segmentation": [],
      "area": 330,
      "bbox": [
        225,
        32,
        15,
        22
      ]
    },
    {
      "id": 8042358611,
      "image_id": 3590137603,
      "category_id": 2000000034,
      "segmentation": [],
      "area": 512,
      "bbox": [
        0,
        0,
        32,
        16
      ]
    },
    {
      "id": 7795517611,
      "image_id": 3590137603,
      "category_id": 2000000034,
      "segmentation": [],
      "area": 254,
      "bbox": [
        64,
        0,
        16,
        16
      ]
    },
    {
      "id": 3408575611,
      "image_id": 3590137603,
      "category_id": 2000000034,
      "segmentation": [],
      "area": 255,
      "bbox": [
        224,
        0,
        16,
        16
      ]
    }
  ],
  "categories": [
    {
      "id": 2000000034,
      "name": "Spider_mites Two-spotted_spider_mite",
      "supercategory": "Tomato"
    }
  ]
}