{
  "info": {
    "description": "data",
    "version": "1.0",
    "year": 2025,
    "contributor": "search engine",
    "source": "no_augmentation",
    "license": {
      "name": "Creative Commons Attribution 4.0 International",
      "url": "https://creativecommons.org/licenses/by/4.0/"
    },
    "leaf_info": {
      "leaf_number": 352.0,
      "source": "plant_village_classification",
      "original_filename": "Com.G_SpM_FL 9386.JPG"
    }
  },
  "images": [
    {
      "id": 4162294002,
      "width": 256,
      "height": 256,
      "file_name": "image (913).JPG",
      "size": 19734,
      "format": "JPG",
      "url": "",
      "hash": "",
      "status": "success",
      "original_filename": "Com.G_SpM_FL 9386.JPG",
      "pvc_filename": "73376b86-f114-44cb-9e4a-c08ad133208c___Com.G_SpM_FL 9386.JPG"
    }
  ],
  "annotations": [
    {
      "id": 3370654018,
      "image_id": 4162294002,
      "category_id": 2000000034,
      "segmentation": [],
      "area": 1941,
      "bbox": [
        61,
        80,
        84,
        167
      ]
    },
    {
      "id": 8325182018,
      "image_id": 4162294002,
      "category_id": 2000000034,
      "segmentation": [],
      "area": 401,
      "bbox": [
        146,
        143,
        46,
        81
      ]
    },
    {
      "id": 8517770018,
      "image_id": 4162294002,
      "category_id": 2000000034,
      "segmentation": [],
      "area": 103,
      "bbox": [
        111,
        142,
        11,
        13
      ]
    },
    {
      "id": 4322591018,
      "image_id": 4162294002,
      "category_id": 2000000034,
      "segmentation": [],
      "area": 1578,
      "bbox": [
        130,
        19,
        91,
        95
      ]
    },
    {
      "id": 9858308018,
      "image_id": 4162294002,
      "category_id": 2000000034,
      "segmentation": [],
      "area": 166,
      "bbox": [
        146,
        86,
        22,
        22
      ]
    },
    {
      "id": 9486194018,
      "image_id": 4162294002,
      "category_id": 2000000034,
      "segmentation": [],
      "area": 1550,
      "bbox": [
        79,
        11,
        47,
        92
      ]
    }
  ],
  "categories": [
    {
      "id": 2000000034,
      "name": "Spider_mites Two-spotted_spider_mite",
      "supercategory": "Tomato"
    }
  ]
}