{
  "info": {
    "description": "data",
    "version": "1.0",
    "year": 2025,
    "contributor": "search engine",
    "source": "no_augmentation",
    "license": {
      "name": "Creative Commons Attribution 4.0 International",
      "url": "https://creativecommons.org/licenses/by/4.0/"
    },
    "leaf_info": {
      "leaf_number": 196.0,
      "source": "plant_village_classification",
      "original_filename": "Com.G_SpM_FL 8551.JPG"
    }
  },
  "images": [
    {
      "id": 6296591231,
      "width": 256,
      "height": 256,
      "file_name": "image (932).JPG",
      "size": 20295,
      "format": "JPG",
      "url": "",
      "hash": "",
      "status": "success",
      "original_filename": "Com.G_SpM_FL 8551.JPG",
      "pvc_filename": "98916e40-9711-49d6-af8b-77c10be459e2___Com.G_SpM_FL 8551.JPG"
    }
  ],
  "annotations": [
    {
      "id": 3823139241,
      "image_id": 6296591231,
      "category_id": 2000000034,
      "segmentation": [],
      "area": 8175,
      "bbox": [
        95,
        21,
        161,
        230
      ]
    },
    {
      "id": 3859570241,
      "image_id": 6296591231,
      "category_id": 2000000034,
      "segmentation": [],
      "area": 152,
      "bbox": [
        106,
        212,
        18,
        26
      ]
    },
    {
      "id": 4808459241,
      "image_id": 6296591231,
      "category_id": 2000000034,
      "segmentation": [],
      "area": 417,
      "bbox": [
        92,
        181,
        37,
        35
      ]
    },
    {
      "id": 2495943241,
      "image_id": 6296591231,
      "category_id": 2000000034,
      "segmentation": [],
      "area": 137,
      "bbox": [
        102,
        157,
        26,
        22
      ]
    },
    {
      "id": 3646201241,
      "image_id": 6296591231,
      "category_id": 2000000034,
      "segmentation": [],
      "area": 329,
      "bbox": [
        136,
        137,
        31,
        43
      ]
    },
    {
      "id": 2858389241,
      "image_id": 6296591231,
      "category_id": 2000000034,
      "segmentation": [],
      "area": 1462,
      "bbox": [
        41,
        118,
        80,
        51
      ]
    },
    {
      "id": 7314878241,
      "image_id": 6296591231,
      "category_id": 2000000034,
      "segmentation": [],
      "area": 243,
      "bbox": [
        176,
        123,
        35,
        22
      ]
    },
    {
      "id": 2177107241,
      "image_id": 6296591231,
      "category_id": 2000000034,
      "segmentation": [],
      "area": 268,
      "bbox": [
        37,
        93,
        42,
        25
      ]
    },
    {
      "id": 2853446241,
      "image_id": 6296591231,
      "category_id": 2000000034,
      "segmentation": [],
      "area": 2683,
      "bbox": [
        25,
        12,
        102,
        93
      ]
    }
  ],
  "categories": [
    {
      "id": 2000000034,
      "name": "Spider_mites Two-spotted_spider_mite",
      "supercategory": "Tomato"
    }
  ]
}