{
  "info": {
    "description": "data",
    "version": "1.0",
    "year": 2025,
    "contributor": "search engine",
    "source": "augmented",
    "license": {
      "name": "Creative Commons Attribution 4.0 International",
      "url": "https://creativecommons.org/licenses/by/4.0/"
    }
  },
  "images": [
    {
      "id": 7041663451,
      "width": 256,
      "height": 256,
      "file_name": "image (751).JPG",
      "size": 16679,
      "format": "JPG",
      "url": "",
      "hash": "",
      "status": "success"
    }
  ],
  "annotations": [
    {
      "id": 4977536460,
      "image_id": 7041663451,
      "category_id": 1000000029,
      "segmentation": [],
      "area": 23142,
      "bbox": [
        33,
        28,
        222,
        228
      ]
    },
    {
      "id": 4227314460,
      "image_id": 7041663451,
      "category_id": 1000000029,
      "segmentation": [],
      "area": 147,
      "bbox": [
        112,
        128,
        16,
        16
      ]
    }
  ],
  "categories": [
    {
      "id": 1000000029,
      "name": "Early_blight",
      "supercategory": "Tomato"
    }
  ]
}