{
  "info": {
    "description": "data",
    "version": "1.0",
    "year": 2025,
    "contributor": "search engine",
    "source": "augmented",
    "license": {
      "name": "Creative Commons Attribution 4.0 International",
      "url": "https://creativecommons.org/licenses/by/4.0/"
    }
  },
  "images": [
    {
      "id": 5245715537,
      "width": 256,
      "height": 256,
      "file_name": "03e8a2f9-6a7e-43dd-8a1b-3eb7cf99b89b___RS_Late.B 5034.JPG",
      "size": 12742,
      "format": "JPG",
      "url": "",
      "hash": "",
      "status": "success",
      "original_filename": "RS_Late.B 5034.JPG",
      "pvc_filename": "03e8a2f9-6a7e-43dd-8a1b-3eb7cf99b89b___RS_Late.B 5034.JPG"
    }
  ],
  "annotations": [
    {
      "id": 2688224543,
      "image_id": 5245715537,
      "category_id": 1000000031,
      "segmentation": [],
      "area": 18986,
      "bbox": [
        37,
        0,
        194,
        256
      ]
    }
  ],
  "categories": [
    {
      "id": 1000000031,
      "name": "Late_blight",
      "supercategory": "Tomato"
    }
  ]
}