{
  "info": {
    "description": "data",
    "version": "1.0",
    "year": 2025,
    "contributor": "search engine",
    "source": "augmented",
    "license": {
      "name": "Creative Commons Attribution 4.0 International",
      "url": "https://creativecommons.org/licenses/by/4.0/"
    }
  },
  "images": [
    {
      "id": 1183696033,
      "width": 204,
      "height": 204,
      "file_name": "image (993).JPG",
      "size": 13179,
      "format": "JPG",
      "url": "",
      "hash": "",
      "status": "success"
    }
  ],
  "annotations": [
    {
      "id": 9308873040,
      "image_id": 1183696033,
      "category_id": 1000000032,
      "segmentation": [],
      "area": 766,
      "bbox": [
        76,
        140,
        41,
        56
      ]
    },
    {
      "id": 2672323040,
      "image_id": 1183696033,
      "category_id": 1000000032,
      "segmentation": [],
      "area": 4335,
      "bbox": [
        0,
        0,
        141,
        182
      ]
    },
    {
      "id": 8015464040,
      "image_id": 1183696033,
      "category_id": 1000000032,
      "segmentation": [],
      "area": 101,
      "bbox": [
        158,
        163,
        11,
        13
      ]
    },
    {
      "id": 4406636040,
      "image_id": 1183696033,
      "category_id": 1000000032,
      "segmentation": [],
      "area": 4484,
      "bbox": [
        92,
        48,
        107,
        102
      ]
    },
    {
      "id": 2465123040,
      "image_id": 1183696033,
      "category_id": 1000000032,
      "segmentation": [],
      "area": 395,
      "bbox": [
        52,
        92,
        19,
        46
      ]
    },
    {
      "id": 9593113040,
      "image_id": 1183696033,
      "category_id": 1000000032,
      "segmentation": [],
      "area": 170,
      "bbox": [
        78,
        107,
        13,
        23
      ]
    },
    {
      "id": 6390598040,
      "image_id": 1183696033,
      "category_id": 1000000032,
      "segmentation": [],
      "area": 113,
      "bbox": [
        80,
        80,
        13,
        16
      ]
    },
    {
      "id": 7579011040,
      "image_id": 1183696033,
      "category_id": 1000000032,
      "segmentation": [],
      "area": 133,
      "bbox": [
        0,
        36,
        9,
        23
      ]
    }
  ],
  "categories": [
    {
      "id": 1000000032,
      "name": "Leaf_Mold",
      "supercategory": "Tomato"
    }
  ]
}