{
  "info": {
    "description": "data",
    "version": "1.0",
    "year": 2025,
    "contributor": "search engine",
    "source": "no_augmentation",
    "license": {
      "name": "Creative Commons Attribution 4.0 International",
      "url": "https://creativecommons.org/licenses/by/4.0/"
    },
    "leaf_info": {}
  },
  "images": [
    {
      "id": 5117801215,
      "width": 256,
      "height": 256,
      "file_name": "image (917).JPG",
      "size": 11241,
      "format": "JPG",
      "url": "",
      "hash": "",
      "status": "success",
      "original_filename": "GHLB2 Leaf 100.1.JPG",
      "pvc_filename": "993ba935-925c-411c-887f-b06670d884c6___GHLB2 Leaf 100.1.JPG"
    }
  ],
  "annotations": [
    {
      "id": 1917434227,
      "image_id": 5117801215,
      "category_id": 2000000031,
      "segmentation": [],
      "area": 2446,
      "bbox": [
        25,
        210,
        119,
        46
      ]
    },
    {
      "id": 6856776227,
      "image_id": 5117801215,
      "category_id": 2000000031,
      "segmentation": [],
      "area": 276,
      "bbox": [
        216,
        213,
        38,
        31
      ]
    },
    {
      "id": 5159195227,
      "image_id": 5117801215,
      "category_id": 2000000031,
      "segmentation": [],
      "area": 2449,
      "bbox": [
        55,
        144,
        70,
        76
      ]
    },
    {
      "id": 4075362227,
      "image_id": 5117801215,
      "category_id": 2000000031,
      "segmentation": [],
      "area": 421,
      "bbox": [
        137,
        183,
        45,
        25
      ]
    },
    {
      "id": 9887258227,
      "image_id": 5117801215,
      "category_id": 2000000031,
      "segmentation": [],
      "area": 5873,
      "bbox": [
        109,
        16,
        105,
        134
      ]
    },
    {
      "id": 3605844227,
      "image_id": 5117801215,
      "category_id": 2000000031,
      "segmentation": [],
      "area": 122,
      "bbox": [
        114,
        33,
        22,
        12
      ]
    }
  ],
  "categories": [
    {
      "id": 2000000031,
      "name": "Late_blight",
      "supercategory": "Tomato"
    }
  ]
}