{
  "info": {
    "description": "data",
    "version": "1.0",
    "year": 2025,
    "contributor": "search engine",
    "source": "no_augmentation",
    "license": {
      "name": "Creative Commons Attribution 4.0 International",
      "url": "https://creativecommons.org/licenses/by/4.0/"
    },
    "leaf_info": {
      "leaf_number": 106.0,
      "source": "plant_village_classification",
      "original_filename": "RS_Late.B 5538.JPG"
    }
  },
  "images": [
    {
      "id": 2633711277,
      "width": 256,
      "height": 256,
      "file_name": "image (853).JPG",
      "size": 16223,
      "format": "JPG",
      "url": "",
      "hash": "",
      "status": "success",
      "original_filename": "RS_Late.B 5538.JPG",
      "pvc_filename": "726a5ae7-e33b-4854-a872-71318ec3a493___RS_Late.B 5538.JPG"
    }
  ],
  "annotations": [
    {
      "id": 2271393283,
      "image_id": 2633711277,
      "category_id": 2000000031,
      "segmentation": [],
      "area": 3445,
      "bbox": [
        20,
        99,
        101,
        140
      ]
    },
    {
      "id": 5175536283,
      "image_id": 2633711277,
      "category_id": 2000000031,
      "segmentation": [],
      "area": 286,
      "bbox": [
        126,
        90,
        28,
        23
      ]
    },
    {
      "id": 1784673283,
      "image_id": 2633711277,
      "category_id": 2000000031,
      "segmentation": [],
      "area": 161,
      "bbox": [
        112,
        90,
        18,
        22
      ]
    },
    {
      "id": 1972686283,
      "image_id": 2633711277,
      "category_id": 2000000031,
      "segmentation": [],
      "area": 306,
      "bbox": [
        86,
        54,
        41,
        21
      ]
    },
    {
      "id": 1910054283,
      "image_id": 2633711277,
      "category_id": 2000000031,
      "segmentation": [],
      "area": 147,
      "bbox": [
        156,
        34,
        35,
        29
      ]
    },
    {
      "id": 3549838283,
      "image_id": 2633711277,
      "category_id": 2000000031,
      "segmentation": [],
      "area": 305,
      "bbox": [
        192,
        8,
        40,
        50
      ]
    },
    {
      "id": 2316404283,
      "image_id": 2633711277,
      "category_id": 2000000031,
      "segmentation": [],
      "area": 109,
      "bbox": [
        135,
        35,
        32,
        14
      ]
    },
    {
      "id": 1928769283,
      "image_id": 2633711277,
      "category_id": 2000000031,
      "segmentation": [],
      "area": 111,
      "bbox": [
        173,
        30,
        25,
        19
      ]
    }
  ],
  "categories": [
    {
      "id": 2000000031,
      "name": "Late_blight",
      "supercategory": "Tomato"
    }
  ]
}