{
  "info": {
    "description": "data",
    "version": "1.0",
    "year": 2025,
    "contributor": "search engine",
    "source": "no_augmentation",
    "license": {
      "name": "Creative Commons Attribution 4.0 International",
      "url": "https://creativecommons.org/licenses/by/4.0/"
    },
    "leaf_info": {
      "leaf_number": 249.0,
      "source": "plant_village_classification",
      "original_filename": "Matt.S_CG 7858.JPG"
    }
  },
  "images": [
    {
      "id": 9907295036,
      "width": 256,
      "height": 256,
      "file_name": "image (1675).JPG",
      "size": 21103,
      "format": "JPG",
      "url": "",
      "hash": "",
      "status": "success",
      "original_filename": "Matt.S_CG 7858.JPG",
      "pvc_filename": "f30ddd54-529d-4e4e-bca6-ddad3a68a690___Matt.S_CG 7858.JPG"
    }
  ],
  "annotations": [
    {
      "id": 7267958045,
      "image_id": 9907295036,
      "category_id": 2000000033,
      "segmentation": [],
      "area": 11342,
      "bbox": [
        119,
        27,
        122,
        223
      ]
    },
    {
      "id": 3346093045,
      "image_id": 9907295036,
      "category_id": 2000000033,
      "segmentation": [],
      "area": 122,
      "bbox": [
        150,
        193,
        10,
        19
      ]
    },
    {
      "id": 8327430045,
      "image_id": 9907295036,
      "category_id": 2000000033,
      "segmentation": [],
      "area": 140,
      "bbox": [
        101,
        180,
        11,
        21
      ]
    },
    {
      "id": 5979238045,
      "image_id": 9907295036,
      "category_id": 2000000033,
      "segmentation": [],
      "area": 102,
      "bbox": [
        54,
        180,
        21,
        15
      ]
    },
    {
      "id": 6447755045,
      "image_id": 9907295036,
      "category_id": 2000000033,
      "segmentation": [],
      "area": 166,
      "bbox": [
        156,
        127,
        19,
        14
      ]
    },
    {
      "id": 7226616045,
      "image_id": 9907295036,
      "category_id": 2000000033,
      "segmentation": [],
      "area": 206,
      "bbox": [
        80,
        117,
        14,
        20
      ]
    },
    {
      "id": 6437880045,
      "image_id": 9907295036,
      "category_id": 2000000033,
      "segmentation": [],
      "area": 352,
      "bbox": [
        93,
        80,
        32,
        31
      ]
    },
    {
      "id": 7053399045,
      "image_id": 9907295036,
      "category_id": 2000000033,
      "segmentation": [],
      "area": 287,
      "bbox": [
        43,
        88,
        60,
        20
      ]
    },
    {
      "id": 9061023045,
      "image_id": 9907295036,
      "category_id": 2000000033,
      "segmentation": [],
      "area": 1198,
      "bbox": [
        21,
        0,
        93,
        77
      ]
    },
    {
      "id": 5412990045,
      "image_id": 9907295036,
      "category_id": 2000000033,
      "segmentation": [],
      "area": 143,
      "bbox": [
        104,
        20,
        40,
        34
      ]
    },
    {
      "id": 9546947045,
      "image_id": 9907295036,
      "category_id": 2000000033,
      "segmentation": [],
      "area": 139,
      "bbox": [
        148,
        20,
        45,
        13
      ]
    }
  ],
  "categories": [
    {
      "id": 2000000033,
      "name": "Septoria_leaf_spot",
      "supercategory": "Tomato"
    }
  ]
}