{
  "info": {
    "description": "data",
    "version": "1.0",
    "year": 2025,
    "contributor": "search engine",
    "source": "no_augmentation",
    "license": {
      "name": "Creative Commons Attribution 4.0 International",
      "url": "https://creativecommons.org/licenses/by/4.0/"
    },
    "leaf_info": {
      "leaf_number": 170.0,
      "source": "plant_village_classification",
      "original_filename": "Matt.S_CG 6871.JPG"
    }
  },
  "images": [
    {
      "id": 3338163574,
      "width": 256,
      "height": 256,
      "file_name": "image (634).JPG",
      "size": 23479,
      "format": "JPG",
      "url": "",
      "hash": "",
      "status": "success",
      "original_filename": "Matt.S_CG 6871.JPG",
      "pvc_filename": "84c0ad52-6b43-43fc-8112-d14f1e9c94c0___Matt.S_CG 6871.JPG"
    }
  ],
  "annotations": [
    {
      "id": 3423485582,
      "image_id": 3338163574,
      "category_id": 2000000033,
      "segmentation": [],
      "area": 20792,
      "bbox": [
        23,
        5,
        207,
        238
      ]
    }
  ],
  "categories": [
    {
      "id": 2000000033,
      "name": "Septoria_leaf_spot",
      "supercategory": "Tomato"
    }
  ]
}