{
  "info": {
    "description": "data",
    "version": "1.0",
    "year": 2025,
    "contributor": "search engine",
    "source": "augmented",
    "license": {
      "name": "Creative Commons Attribution 4.0 International",
      "url": "https://creativecommons.org/licenses/by/4.0/"
    }
  },
  "images": [
    {
      "id": 4611112452,
      "width": 256,
      "height": 256,
      "file_name": "534e3551-79be-4101-92ac-2996761db483___Crnl_L.Mold 6707.JPG",
      "size": 11849,
      "format": "JPG",
      "url": "",
      "hash": "",
      "status": "success",
      "original_filename": "Crnl_L.Mold 6707.JPG",
      "pvc_filename": "534e3551-79be-4101-92ac-2996761db483___Crnl_L.Mold 6707.JPG"
    }
  ],
  "annotations": [
    {
      "id": 5476751461,
      "image_id": 4611112452,
      "category_id": 1000000032,
      "segmentation": [],
      "area": 111,
      "bbox": [
        174,
        205,
        17,
        23
      ]
    },
    {
      "id": 9039534461,
      "image_id": 4611112452,
      "category_id": 1000000032,
      "segmentation": [],
      "area": 164,
      "bbox": [
        174,
        143,
        13,
        50
      ]
    },
    {
      "id": 4466473461,
      "image_id": 4611112452,
      "category_id": 1000000032,
      "segmentation": [],
      "area": 243,
      "bbox": [
        138,
        158,
        19,
        33
      ]
    },
    {
      "id": 3313646461,
      "image_id": 4611112452,
      "category_id": 1000000032,
      "segmentation": [],
      "area": 799,
      "bbox": [
        104,
        111,
        41,
        65
      ]
    },
    {
      "id": 7327747461,
      "image_id": 4611112452,
      "category_id": 1000000032,
      "segmentation": [],
      "area": 103,
      "bbox": [
        91,
        132,
        16,
        14
      ]
    },
    {
      "id": 4345305461,
      "image_id": 4611112452,
      "category_id": 1000000032,
      "segmentation": [],
      "area": 109,
      "bbox": [
        74,
        112,
        15,
        21
      ]
    },
    {
      "id": 7104527462,
      "image_id": 4611112452,
      "category_id": 1000000032,
      "segmentation": [],
      "area": 1516,
      "bbox": [
        48,
        66,
        46,
        53
      ]
    }
  ],
  "categories": [
    {
      "id": 1000000032,
      "name": "Leaf_Mold",
      "supercategory": "Tomato"
    }
  ]
}