{
  "info": {
    "description": "data",
    "version": "1.0",
    "year": 2025,
    "contributor": "search engine",
    "source": "augmented",
    "license": {
      "name": "Creative Commons Attribution 4.0 International",
      "url": "https://creativecommons.org/licenses/by/4.0/"
    }
  },
  "images": [
    {
      "id": 3981841537,
      "width": 256,
      "height": 256,
      "file_name": "image (1145).JPG",
      "size": 26515,
      "format": "JPG",
      "url": "",
      "hash": "",
      "status": "success"
    }
  ],
  "annotations": [
    {
      "id": 3046943546,
      "image_id": 3981841537,
      "category_id": 1000000030,
      "segmentation": [],
      "area": 4007,
      "bbox": [
        131,
        80,
        114,
        176
      ]
    },
    {
      "id": 8452081546,
      "image_id": 3981841537,
      "category_id": 1000000030,
      "segmentation": [],
      "area": 320,
      "bbox": [
        80,
        161,
        55,
        33
      ]
    },
    {
      "id": 8871613546,
      "image_id": 3981841537,
      "category_id": 1000000030,
      "segmentation": [],
      "area": 4165,
      "bbox": [
        72,
        30,
        126,
        121
      ]
    },
    {
      "id": 6685623546,
      "image_id": 3981841537,
      "category_id": 1000000030,
      "segmentation": [],
      "area": 162,
      "bbox": [
        44,
        125,
        25,
        13
      ]
    },
    {
      "id": 3510730546,
      "image_id": 3981841537,
      "category_id": 1000000030,
      "segmentation": [],
      "area": 282,
      "bbox": [
        35,
        71,
        48,
        28
      ]
    },
    {
      "id": 9287770546,
      "image_id": 3981841537,
      "category_id": 1000000030,
      "segmentation": [],
      "area": 202,
      "bbox": [
        72,
        49,
        42,
        26
      ]
    },
    {
      "id": 3046487546,
      "image_id": 3981841537,
      "category_id": 1000000030,
      "segmentation": [],
      "area": 125,
      "bbox": [
        54,
        30,
        22,
        17
      ]
    },
    {
      "id": 5949214546,
      "image_id": 3981841537,
      "category_id": 1000000030,
      "segmentation": [],
      "area": 288,
      "bbox": [
        62,
        16,
        37,
        23
      ]
    },
    {
      "id": 3173070546,
      "image_id": 3981841537,
      "category_id": 1000000030,
      "segmentation": [],
      "area": 355,
      "bbox": [
        138,
        6,
        52,
        19
      ]
    },
    {
      "id": 6238736546,
      "image_id": 3981841537,
      "category_id": 1000000030,
      "segmentation": [],
      "area": 103,
      "bbox": [
        117,
        2,
        29,
        8
      ]
    }
  ],
  "categories": [
    {
      "id": 1000000030,
      "name": "healthy",
      "supercategory": "Tomato"
    }
  ]
}