{
  "info": {
    "description": "data",
    "version": "1.0",
    "year": 2025,
    "contributor": "search engine",
    "source": "no_augmentation",
    "license": {
      "name": "Creative Commons Attribution 4.0 International",
      "url": "https://creativecommons.org/licenses/by/4.0/"
    },
    "leaf_info": {}
  },
  "images": [
    {
      "id": 5042697171,
      "width": 256,
      "height": 256,
      "file_name": "image (1233).JPG",
      "size": 19925,
      "format": "JPG",
      "url": "",
      "hash": "",
      "status": "success",
      "original_filename": "Com.G_TgS_FL 9965.JPG",
      "pvc_filename": "e9c43f84-89b5-4e72-b6fd-da5698f342c2___Com.G_TgS_FL 9965.JPG"
    }
  ],
  "annotations": [
    {
      "id": 3464959180,
      "image_id": 5042697171,
      "category_id": 2000000035,
      "segmentation": [],
      "area": 6653,
      "bbox": [
        46,
        58,
        162,
        198
      ]
    },
    {
      "id": 8964670180,
      "image_id": 5042697171,
      "category_id": 2000000035,
      "segmentation": [],
      "area": 182,
      "bbox": [
        138,
        188,
        21,
        16
      ]
    },
    {
      "id": 9402277180,
      "image_id": 5042697171,
      "category_id": 2000000035,
      "segmentation": [],
      "area": 234,
      "bbox": [
        61,
        166,
        26,
        20
      ]
    },
    {
      "id": 2078327180,
      "image_id": 5042697171,
      "category_id": 2000000035,
      "segmentation": [],
      "area": 256,
      "bbox": [
        80,
        114,
        32,
        14
      ]
    },
    {
      "id": 3231027180,
      "image_id": 5042697171,
      "category_id": 2000000035,
      "segmentation": [],
      "area": 316,
      "bbox": [
        194,
        90,
        41,
        36
      ]
    },
    {
      "id": 4831575180,
      "image_id": 5042697171,
      "category_id": 2000000035,
      "segmentation": [],
      "area": 121,
      "bbox": [
        62,
        98,
        19,
        14
      ]
    },
    {
      "id": 9565198180,
      "image_id": 5042697171,
      "category_id": 2000000035,
      "segmentation": [],
      "area": 1912,
      "bbox": [
        73,
        15,
        73,
        89
      ]
    },
    {
      "id": 5807356180,
      "image_id": 5042697171,
      "category_id": 2000000035,
      "segmentation": [],
      "area": 150,
      "bbox": [
        80,
        85,
        16,
        12
      ]
    },
    {
      "id": 8797814180,
      "image_id": 5042697171,
      "category_id": 2000000035,
      "segmentation": [],
      "area": 430,
      "bbox": [
        165,
        32,
        66,
        55
      ]
    }
  ],
  "categories": [
    {
      "id": 2000000035,
      "name": "Target_Spot",
      "supercategory": "Tomato"
    }
  ]
}