{
  "info": {
    "description": "data",
    "version": "1.0",
    "year": 2025,
    "contributor": "search engine",
    "source": "no_augmentation",
    "license": {
      "name": "Creative Commons Attribution 4.0 International",
      "url": "https://creativecommons.org/licenses/by/4.0/"
    },
    "leaf_info": {}
  },
  "images": [
    {
      "id": 8370277664,
      "width": 256,
      "height": 256,
      "file_name": "image (235).JPG",
      "size": 21903,
      "format": "JPG",
      "url": "",
      "hash": "",
      "status": "success",
      "original_filename": "Com.G_TgS_FL 0768.JPG",
      "pvc_filename": "7a911998-4bc2-4949-93a1-050d7cedca01___Com.G_TgS_FL 0768.JPG"
    }
  ],
  "annotations": [
    {
      "id": 5753024673,
      "image_id": 8370277664,
      "category_id": 2000000035,
      "segmentation": [],
      "area": 279,
      "bbox": [
        144,
        225,
        40,
        16
      ]
    },
    {
      "id": 5125567673,
      "image_id": 8370277664,
      "category_id": 2000000035,
      "segmentation": [],
      "area": 107,
      "bbox": [
        129,
        197,
        20,
        16
      ]
    },
    {
      "id": 2208124673,
      "image_id": 8370277664,
      "category_id": 2000000035,
      "segmentation": [],
      "area": 189,
      "bbox": [
        155,
        87,
        35,
        16
      ]
    },
    {
      "id": 7576658673,
      "image_id": 8370277664,
      "category_id": 2000000035,
      "segmentation": [],
      "area": 122,
      "bbox": [
        26,
        57,
        25,
        24
      ]
    },
    {
      "id": 3619167673,
      "image_id": 8370277664,
      "category_id": 2000000035,
      "segmentation": [],
      "area": 874,
      "bbox": [
        114,
        14,
        82,
        67
      ]
    },
    {
      "id": 8552891673,
      "image_id": 8370277664,
      "category_id": 2000000035,
      "segmentation": [],
      "area": 574,
      "bbox": [
        46,
        11,
        67,
        36
      ]
    }
  ],
  "categories": [
    {
      "id": 2000000035,
      "name": "Target_Spot",
      "supercategory": "Tomato"
    }
  ]
}