{
  "info": {
    "description": "data",
    "version": "1.0",
    "year": 2025,
    "contributor": "search engine",
    "source": "no_augmentation",
    "license": {
      "name": "Creative Commons Attribution 4.0 International",
      "url": "https://creativecommons.org/licenses/by/4.0/"
    },
    "leaf_info": {}
  },
  "images": [
    {
      "id": 4779570672,
      "width": 256,
      "height": 256,
      "file_name": "image (794).JPG",
      "size": 19521,
      "format": "JPG",
      "url": "",
      "hash": "",
      "status": "success",
      "original_filename": "Com.G_TgS_FL 8066.JPG",
      "pvc_filename": "540358b3-4832-42fb-92d0-d270e61cb9da___Com.G_TgS_FL 8066.JPG"
    }
  ],
  "annotations": [
    {
      "id": 6849246680,
      "image_id": 4779570672,
      "category_id": 2000000035,
      "segmentation": [],
      "area": 562,
      "bbox": [
        116,
        159,
        22,
        70
      ]
    },
    {
      "id": 8671734680,
      "image_id": 4779570672,
      "category_id": 2000000035,
      "segmentation": [],
      "area": 111,
      "bbox": [
        102,
        191,
        10,
        24
      ]
    },
    {
      "id": 9508009680,
      "image_id": 4779570672,
      "category_id": 2000000035,
      "segmentation": [],
      "area": 4521,
      "bbox": [
        157,
        0,
        99,
        216
      ]
    },
    {
      "id": 1662626680,
      "image_id": 4779570672,
      "category_id": 2000000035,
      "segmentation": [],
      "area": 2180,
      "bbox": [
        22,
        32,
        67,
        100
      ]
    },
    {
      "id": 6037720680,
      "image_id": 4779570672,
      "category_id": 2000000035,
      "segmentation": [],
      "area": 156,
      "bbox": [
        137,
        92,
        29,
        26
      ]
    },
    {
      "id": 2791261680,
      "image_id": 4779570672,
      "category_id": 2000000035,
      "segmentation": [],
      "area": 253,
      "bbox": [
        125,
        16,
        41,
        33
      ]
    },
    {
      "id": 6114421680,
      "image_id": 4779570672,
      "category_id": 2000000035,
      "segmentation": [],
      "area": 156,
      "bbox": [
        42,
        20,
        23,
        16
      ]
    },
    {
      "id": 7315777680,
      "image_id": 4779570672,
      "category_id": 2000000035,
      "segmentation": [],
      "area": 142,
      "bbox": [
        104,
        0,
        10,
        30
      ]
    },
    {
      "id": 6191469680,
      "image_id": 4779570672,
      "category_id": 2000000035,
      "segmentation": [],
      "area": 185,
      "bbox": [
        74,
        0,
        27,
        17
      ]
    }
  ],
  "categories": [
    {
      "id": 2000000035,
      "name": "Target_Spot",
      "supercategory": "Tomato"
    }
  ]
}