{
  "info": {
    "description": "data",
    "version": "1.0",
    "year": 2025,
    "contributor": "search engine",
    "source": "augmented",
    "license": {
      "name": "Creative Commons Attribution 4.0 International",
      "url": "https://creativecommons.org/licenses/by/4.0/"
    }
  },
  "images": [
    {
      "id": 3228608902,
      "width": 256,
      "height": 256,
      "file_name": "image (710).JPG",
      "size": 19580,
      "format": "JPG",
      "url": "",
      "hash": "",
      "status": "success"
    }
  ],
  "annotations": [
    {
      "id": 8126171910,
      "image_id": 3228608902,
      "category_id": 1000000034,
      "segmentation": [],
      "area": 8639,
      "bbox": [
        43,
        0,
        182,
        244
      ]
    },
    {
      "id": 1543056910,
      "image_id": 3228608902,
      "category_id": 1000000034,
      "segmentation": [],
      "area": 289,
      "bbox": [
        87,
        154,
        25,
        45
      ]
    },
    {
      "id": 6223881910,
      "image_id": 3228608902,
      "category_id": 1000000034,
      "segmentation": [],
      "area": 740,
      "bbox": [
        78,
        114,
        42,
        66
      ]
    },
    {
      "id": 8946587910,
      "image_id": 3228608902,
      "category_id": 1000000034,
      "segmentation": [],
      "area": 142,
      "bbox": [
        83,
        95,
        38,
        17
      ]
    }
  ],
  "categories": [
    {
      "id": 1000000034,
      "name": "Spider_mites Two-spotted_spider_mite",
      "supercategory": "Tomato"
    }
  ]
}