{
  "info": {
    "description": "data",
    "version": "1.0",
    "year": 2025,
    "contributor": "search engine",
    "source": "no_augmentation",
    "license": {
      "name": "Creative Commons Attribution 4.0 International",
      "url": "https://creativecommons.org/licenses/by/4.0/"
    },
    "leaf_info": {
      "leaf_number": 55.0,
      "source": "plant_village_classification",
      "original_filename": "Crnl_L.Mold 6771.JPG"
    }
  },
  "images": [
    {
      "id": 4908110941,
      "width": 256,
      "height": 256,
      "file_name": "image (486).JPG",
      "size": 16946,
      "format": "JPG",
      "url": "",
      "hash": "",
      "status": "success",
      "original_filename": "Crnl_L.Mold 6771.JPG",
      "pvc_filename": "7922fafa-294f-4a34-999a-040d1a1a1d44___Crnl_L.Mold 6771.JPG"
    }
  ],
  "annotations": [
    {
      "id": 7160270949,
      "image_id": 4908110941,
      "category_id": 2000000032,
      "segmentation": [],
      "area": 114,
      "bbox": [
        80,
        196,
        33,
        30
      ]
    },
    {
      "id": 3601553949,
      "image_id": 4908110941,
      "category_id": 2000000032,
      "segmentation": [],
      "area": 180,
      "bbox": [
        61,
        163,
        18,
        31
      ]
    },
    {
      "id": 9750745949,
      "image_id": 4908110941,
      "category_id": 2000000032,
      "segmentation": [],
      "area": 132,
      "bbox": [
        60,
        140,
        13,
        22
      ]
    },
    {
      "id": 3700329949,
      "image_id": 4908110941,
      "category_id": 2000000032,
      "segmentation": [],
      "area": 8811,
      "bbox": [
        21,
        0,
        196,
        145
      ]
    },
    {
      "id": 7152748949,
      "image_id": 4908110941,
      "category_id": 2000000032,
      "segmentation": [],
      "area": 307,
      "bbox": [
        77,
        83,
        49,
        41
      ]
    },
    {
      "id": 8358285949,
      "image_id": 4908110941,
      "category_id": 2000000032,
      "segmentation": [],
      "area": 537,
      "bbox": [
        89,
        53,
        53,
        22
      ]
    }
  ],
  "categories": [
    {
      "id": 2000000032,
      "name": "Leaf_Mold",
      "supercategory": "Tomato"
    }
  ]
}