{
  "info": {
    "description": "data",
    "version": "1.0",
    "year": 2025,
    "contributor": "search engine",
    "source": "augmented",
    "license": {
      "name": "Creative Commons Attribution 4.0 International",
      "url": "https://creativecommons.org/licenses/by/4.0/"
    }
  },
  "images": [
    {
      "id": 7623289409,
      "width": 256,
      "height": 256,
      "file_name": "image (1335).JPG",
      "size": 11097,
      "format": "JPG",
      "url": "",
      "hash": "",
      "status": "success"
    }
  ],
  "annotations": [
    {
      "id": 4802373418,
      "image_id": 7623289409,
      "category_id": 1000000031,
      "segmentation": [],
      "area": 115,
      "bbox": [
        130,
        204,
        11,
        29
      ]
    },
    {
      "id": 7342736418,
      "image_id": 7623289409,
      "category_id": 1000000031,
      "segmentation": [],
      "area": 887,
      "bbox": [
        142,
        149,
        52,
        31
      ]
    },
    {
      "id": 8408147418,
      "image_id": 7623289409,
      "category_id": 1000000031,
      "segmentation": [],
      "area": 110,
      "bbox": [
        200,
        135,
        12,
        32
      ]
    },
    {
      "id": 8641391418,
      "image_id": 7623289409,
      "category_id": 1000000031,
      "segmentation": [],
      "area": 2781,
      "bbox": [
        56,
        87,
        84,
        76
      ]
    },
    {
      "id": 5112638418,
      "image_id": 7623289409,
      "category_id": 1000000031,
      "segmentation": [],
      "area": 3652,
      "bbox": [
        106,
        16,
        102,
        102
      ]
    }
  ],
  "categories": [
    {
      "id": 1000000031,
      "name": "Late_blight",
      "supercategory": "Tomato"
    }
  ]
}