{
  "info": {
    "description": "data",
    "version": "1.0",
    "year": 2025,
    "contributor": "search engine",
    "source": "augmented",
    "license": {
      "name": "Creative Commons Attribution 4.0 International",
      "url": "https://creativecommons.org/licenses/by/4.0/"
    }
  },
  "images": [
    {
      "id": 5800910043,
      "width": 256,
      "height": 256,
      "file_name": "image (424).JPG",
      "size": 16535,
      "format": "JPG",
      "url": "",
      "hash": "",
      "status": "success"
    }
  ],
  "annotations": [
    {
      "id": 7796507049,
      "image_id": 5800910043,
      "category_id": 1000000031,
      "segmentation": [],
      "area": 801,
      "bbox": [
        60,
        162,
        68,
        85
      ]
    },
    {
      "id": 8924314049,
      "image_id": 5800910043,
      "category_id": 1000000031,
      "segmentation": [],
      "area": 509,
      "bbox": [
        176,
        114,
        58,
        117
      ]
    },
    {
      "id": 3845589049,
      "image_id": 5800910043,
      "category_id": 1000000031,
      "segmentation": [],
      "area": 560,
      "bbox": [
        38,
        114,
        41,
        52
      ]
    },
    {
      "id": 8609485049,
      "image_id": 5800910043,
      "category_id": 1000000031,
      "segmentation": [],
      "area": 420,
      "bbox": [
        66,
        109,
        61,
        21
      ]
    },
    {
      "id": 9652511049,
      "image_id": 5800910043,
      "category_id": 1000000031,
      "segmentation": [],
      "area": 1159,
      "bbox": [
        11,
        70,
        74,
        48
      ]
    },
    {
      "id": 2112412049,
      "image_id": 5800910043,
      "category_id": 1000000031,
      "segmentation": [],
      "area": 111,
      "bbox": [
        46,
        87,
        42,
        18
      ]
    },
    {
      "id": 4629502049,
      "image_id": 5800910043,
      "category_id": 1000000031,
      "segmentation": [],
      "area": 9414,
      "bbox": [
        16,
        0,
        216,
        97
      ]
    },
    {
      "id": 4763346049,
      "image_id": 5800910043,
      "category_id": 1000000031,
      "segmentation": [],
      "area": 102,
      "bbox": [
        188,
        24,
        26,
        13
      ]
    }
  ],
  "categories": [
    {
      "id": 1000000031,
      "name": "Late_blight",
      "supercategory": "Tomato"
    }
  ]
}