{
  "info": {
    "description": "data",
    "version": "1.0",
    "year": 2025,
    "contributor": "search engine",
    "source": "augmented",
    "license": {
      "name": "Creative Commons Attribution 4.0 International",
      "url": "https://creativecommons.org/licenses/by/4.0/"
    }
  },
  "images": [
    {
      "id": 1571593807,
      "width": 256,
      "height": 256,
      "file_name": "74bd9dda-a761-4cea-94d9-7b93190bd88d___Com.G_SpM_FL 1633.JPG",
      "size": 21188,
      "format": "JPG",
      "url": "",
      "hash": "",
      "status": "success",
      "original_filename": "Com.G_SpM_FL 1633.JPG",
      "pvc_filename": "74bd9dda-a761-4cea-94d9-7b93190bd88d___Com.G_SpM_FL 1633.JPG"
    }
  ],
  "annotations": [
    {
      "id": 4845411819,
      "image_id": 1571593807,
      "category_id": 1000000034,
      "segmentation": [],
      "area": 6492,
      "bbox": [
        36,
        0,
        180,
        194
      ]
    },
    {
      "id": 2521949819,
      "image_id": 1571593807,
      "category_id": 1000000034,
      "segmentation": [],
      "area": 102,
      "bbox": [
        90,
        146,
        15,
        14
      ]
    },
    {
      "id": 8544966819,
      "image_id": 1571593807,
      "category_id": 1000000034,
      "segmentation": [],
      "area": 255,
      "bbox": [
        161,
        63,
        31,
        38
      ]
    }
  ],
  "categories": [
    {
      "id": 1000000034,
      "name": "Spider_mites Two-spotted_spider_mite",
      "supercategory": "Tomato"
    }
  ]
}