{
  "info": {
    "description": "data",
    "version": "1.0",
    "year": 2025,
    "contributor": "search engine",
    "source": "no_augmentation",
    "license": {
      "name": "Creative Commons Attribution 4.0 International",
      "url": "https://creativecommons.org/licenses/by/4.0/"
    },
    "leaf_info": {
      "leaf_number": 245.0,
      "source": "plant_village_classification",
      "original_filename": "RS_HL 9972.JPG"
    }
  },
  "images": [
    {
      "id": 1544897712,
      "width": 256,
      "height": 256,
      "file_name": "image (390).JPG",
      "size": 25541,
      "format": "JPG",
      "url": "",
      "hash": "",
      "status": "success",
      "original_filename": "RS_HL 9972.JPG",
      "pvc_filename": "9b668abb-fc96-412e-948f-442af45ec580___RS_HL 9972.JPG"
    }
  ],
  "annotations": [
    {
      "id": 9187591722,
      "image_id": 1544897712,
      "category_id": 2000000030,
      "segmentation": [],
      "area": 2658,
      "bbox": [
        70,
        144,
        171,
        112
      ]
    },
    {
      "id": 1436129722,
      "image_id": 1544897712,
      "category_id": 2000000030,
      "segmentation": [],
      "area": 248,
      "bbox": [
        141,
        164,
        36,
        32
      ]
    },
    {
      "id": 2291859722,
      "image_id": 1544897712,
      "category_id": 2000000030,
      "segmentation": [],
      "area": 167,
      "bbox": [
        196,
        148,
        14,
        37
      ]
    },
    {
      "id": 9853289722,
      "image_id": 1544897712,
      "category_id": 2000000030,
      "segmentation": [],
      "area": 3497,
      "bbox": [
        78,
        0,
        83,
        177
      ]
    },
    {
      "id": 5055298722,
      "image_id": 1544897712,
      "category_id": 2000000030,
      "segmentation": [],
      "area": 252,
      "bbox": [
        173,
        124,
        34,
        21
      ]
    },
    {
      "id": 4879070722,
      "image_id": 1544897712,
      "category_id": 2000000030,
      "segmentation": [],
      "area": 1394,
      "bbox": [
        16,
        73,
        82,
        59
      ]
    },
    {
      "id": 6911446722,
      "image_id": 1544897712,
      "category_id": 2000000030,
      "segmentation": [],
      "area": 110,
      "bbox": [
        74,
        112,
        22,
        16
      ]
    },
    {
      "id": 7287763722,
      "image_id": 1544897712,
      "category_id": 2000000030,
      "segmentation": [],
      "area": 729,
      "bbox": [
        152,
        63,
        51,
        54
      ]
    },
    {
      "id": 6219111722,
      "image_id": 1544897712,
      "category_id": 2000000030,
      "segmentation": [],
      "area": 155,
      "bbox": [
        128,
        77,
        18,
        19
      ]
    },
    {
      "id": 5661156722,
      "image_id": 1544897712,
      "category_id": 2000000030,
      "segmentation": [],
      "area": 275,
      "bbox": [
        19,
        37,
        39,
        21
      ]
    }
  ],
  "categories": [
    {
      "id": 2000000030,
      "name": "healthy",
      "supercategory": "Tomato"
    }
  ]
}