{
  "info": {
    "description": "data",
    "version": "1.0",
    "year": 2025,
    "contributor": "search engine",
    "source": "no_augmentation",
    "license": {
      "name": "Creative Commons Attribution 4.0 International",
      "url": "https://creativecommons.org/licenses/by/4.0/"
    },
    "leaf_info": {
      "leaf_number": 23.0,
      "source": "plant_village_classification",
      "original_filename": "RS_HL 0488.JPG"
    }
  },
  "images": [
    {
      "id": 2211126620,
      "width": 256,
      "height": 256,
      "file_name": "image (1359).JPG",
      "size": 24819,
      "format": "JPG",
      "url": "",
      "hash": "",
      "status": "success",
      "original_filename": "RS_HL 0488.JPG",
      "pvc_filename": "d9756e4c-11ac-4c09-8a3c-4938d56bfc1e___RS_HL 0488.JPG"
    }
  ],
  "annotations": [
    {
      "id": 2958593631,
      "image_id": 2211126620,
      "category_id": 2000000030,
      "segmentation": [],
      "area": 12063,
      "bbox": [
        0,
        48,
        202,
        207
      ]
    },
    {
      "id": 8256923631,
      "image_id": 2211126620,
      "category_id": 2000000030,
      "segmentation": [],
      "area": 541,
      "bbox": [
        89,
        181,
        27,
        39
      ]
    },
    {
      "id": 3672340631,
      "image_id": 2211126620,
      "category_id": 2000000030,
      "segmentation": [],
      "area": 823,
      "bbox": [
        175,
        76,
        49,
        71
      ]
    },
    {
      "id": 7453840631,
      "image_id": 2211126620,
      "category_id": 2000000030,
      "segmentation": [],
      "area": 226,
      "bbox": [
        144,
        100,
        31,
        16
      ]
    },
    {
      "id": 4272432631,
      "image_id": 2211126620,
      "category_id": 2000000030,
      "segmentation": [],
      "area": 101,
      "bbox": [
        157,
        77,
        20,
        13
      ]
    },
    {
      "id": 4306209631,
      "image_id": 2211126620,
      "category_id": 2000000030,
      "segmentation": [],
      "area": 155,
      "bbox": [
        184,
        59,
        34,
        18
      ]
    },
    {
      "id": 3425723631,
      "image_id": 2211126620,
      "category_id": 2000000030,
      "segmentation": [],
      "area": 2244,
      "bbox": [
        67,
        14,
        135,
        48
      ]
    }
  ],
  "categories": [
    {
      "id": 2000000030,
      "name": "healthy",
      "supercategory": "Tomato"
    }
  ]
}