{
  "info": {
    "description": "data",
    "version": "1.0",
    "year": 2025,
    "contributor": "search engine",
    "source": "no_augmentation",
    "license": {
      "name": "Creative Commons Attribution 4.0 International",
      "url": "https://creativecommons.org/licenses/by/4.0/"
    },
    "leaf_info": {
      "leaf_number": 37.0,
      "source": "plant_village_classification",
      "original_filename": "RS_HL 0147.JPG"
    }
  },
  "images": [
    {
      "id": 4912016635,
      "width": 256,
      "height": 256,
      "file_name": "image (136).JPG",
      "size": 26236,
      "format": "JPG",
      "url": "",
      "hash": "",
      "status": "success",
      "original_filename": "RS_HL 0147.JPG",
      "pvc_filename": "2fb5c266-b7ec-4b31-91b4-3f2dc9b0cdcb___RS_HL 0147.JPG"
    }
  ],
  "annotations": [
    {
      "id": 1740254645,
      "image_id": 4912016635,
      "category_id": 2000000030,
      "segmentation": [],
      "area": 256,
      "bbox": [
        143,
        207,
        19,
        42
      ]
    },
    {
      "id": 6093692645,
      "image_id": 4912016635,
      "category_id": 2000000030,
      "segmentation": [],
      "area": 174,
      "bbox": [
        140,
        180,
        9,
        43
      ]
    },
    {
      "id": 1295037645,
      "image_id": 4912016635,
      "category_id": 2000000030,
      "segmentation": [],
      "area": 260,
      "bbox": [
        163,
        186,
        29,
        24
      ]
    },
    {
      "id": 7793036645,
      "image_id": 4912016635,
      "category_id": 2000000030,
      "segmentation": [],
      "area": 104,
      "bbox": [
        134,
        150,
        11,
        24
      ]
    },
    {
      "id": 8844109645,
      "image_id": 4912016635,
      "category_id": 2000000030,
      "segmentation": [],
      "area": 124,
      "bbox": [
        47,
        137,
        30,
        18
      ]
    },
    {
      "id": 1314289645,
      "image_id": 4912016635,
      "category_id": 2000000030,
      "segmentation": [],
      "area": 243,
      "bbox": [
        79,
        106,
        17,
        42
      ]
    },
    {
      "id": 9800415645,
      "image_id": 4912016635,
      "category_id": 2000000030,
      "segmentation": [],
      "area": 124,
      "bbox": [
        176,
        127,
        19,
        13
      ]
    },
    {
      "id": 8745015645,
      "image_id": 4912016635,
      "category_id": 2000000030,
      "segmentation": [],
      "area": 576,
      "bbox": [
        26,
        78,
        45,
        53
      ]
    },
    {
      "id": 3707955645,
      "image_id": 4912016635,
      "category_id": 2000000030,
      "segmentation": [],
      "area": 237,
      "bbox": [
        47,
        94,
        39,
        18
      ]
    },
    {
      "id": 8678327645,
      "image_id": 4912016635,
      "category_id": 2000000030,
      "segmentation": [],
      "area": 3112,
      "bbox": [
        33,
        0,
        160,
        87
      ]
    },
    {
      "id": 3160401645,
      "image_id": 4912016635,
      "category_id": 2000000030,
      "segmentation": [],
      "area": 1336,
      "bbox": [
        2,
        37,
        91,
        39
      ]
    }
  ],
  "categories": [
    {
      "id": 2000000030,
      "name": "healthy",
      "supercategory": "Tomato"
    }
  ]
}